{
  "parent": "minecraft:recipes/root",
  "rewards": {
    "recipes": [
      "janoeo:blasting_emerald_end_ore_to_emerald"
    ]
  },
  "criteria": {
    "has_end_emerald_ore": {
      "trigger": "minecraft:inventory_changed",
      "conditions": {
        "items": [
          {
            "item": "janoeo:emerald_end_ore"
          }
        ]
      }
    },
    "has_the_recipe": {
      "trigger": "minecraft:recipe_unlocked",
      "conditions": {
        "recipe": "janoeo:blasting_emerald_end_ore_to_emerald"
      }
    }
  },
  "requirements": [
    [
      "has_end_emerald_ore",
      "has_the_recipe"
    ]
  ]
}